chquery/__init__.py
chquery-0.0.2.dist-info/licenses/LICENSE
chquery-0.0.2.dist-info/METADATA
chquery-0.0.2.dist-info/WHEEL
chquery-0.0.2.dist-info/top_level.txt
chquery-0.0.2.dist-info/RECORD
