Metadata-Version: 2.4
Name: chquery
Version: 0.0.2
Summary: CHQuery is an async Python client and query builder for ClickHouse, built on top of asynch using native TCP connection for speed.
Author-email: Filip Nyquist <nyquistfilip@gmail.com>
License-Expression: MIT
Project-URL: Homepage, https://github.com/filipnyquist/chquery
Project-URL: Issues, https://github.com/filipnyquist/chquery/issues
Classifier: Programming Language :: Python :: 3
Classifier: Operating System :: OS Independent
Classifier: Development Status :: 4 - Beta
Classifier: Topic :: Database
Requires-Python: >=3.10
License-File: LICENSE
Requires-Dist: asynch[compression]>=0.3.0
Dynamic: license-file
